fstrent_tools/__init__.py
fstrent_tools/tools_convert.py
fstrent_tools/tools_debug.py
fstrent_tools/tools_decorators.py
fstrent_tools/tools_dicts.py
fstrent_tools/tools_docs.py
fstrent_tools/tools_errors.py
fstrent_tools/tools_eval.py
fstrent_tools/tools_files.py
fstrent_tools/tools_formatting.py
fstrent_tools/tools_hyperlinks.py
fstrent_tools/tools_json.py
fstrent_tools/tools_logging.py
fstrent_tools/tools_object.py
fstrent_tools/tools_print.py
fstrent_tools/tools_python.py
fstrent_tools/tools_settings.py
fstrent_tools/tools_sounds.py
fstrent_tools/tools_speak.py
fstrent_tools/tools_strings.py
fstrent_tools/tools_terminal.py
fstrent_tools/tools_time.py
fstrent_tools/tools_types.py
fstrent_tools/tools_voice.py
sounds/cashreg.wav
sounds/doh.wav
sounds/spysound.wav
sounds/thunder.wav
sounds/wolf.wav
sounds/wolf2.wav
fstrent_tools-0.9.2.dist-info/LICENSE
fstrent_tools-0.9.2.dist-info/METADATA
fstrent_tools-0.9.2.dist-info/WHEEL
fstrent_tools-0.9.2.dist-info/top_level.txt
fstrent_tools-0.9.2.dist-info/RECORD
