Metadata-Version: 2.1
Name: fstrent_tools
Version: 0.9.2
Summary: A collection of Python utility functions
Home-page: https://github.com/wrm3/fstrent_tools
Author: FSTrent
Author-email: FSTrent <wrmartel3@gmail.com>
Project-URL: Homepage, https://github.com/wrm3/fstrent_tools
Project-URL: Bug Tracker, https://github.com/wrm3/fstrent_tools/issues
Classifier: Programming Language :: Python :: 3
Classifier: License :: OSI Approved :: MIT License
Classifier: Operating System :: OS Independent
Requires-Python: >=3.6
License-File: LICENSE
